azureml/__init__.py
azureml/contrib/__init__.py
azureml_contrib_itp-0.0.1.dist-info/LICENSE.txt
azureml_contrib_itp-0.0.1.dist-info/METADATA
azureml_contrib_itp-0.0.1.dist-info/WHEEL
azureml_contrib_itp-0.0.1.dist-info/top_level.txt
azureml_contrib_itp-0.0.1.dist-info/RECORD
